ontoeval/__init__.py
ontoeval/cli.py
ontoeval/github.py
ontoeval/models.py
ontoeval/runner.py
ontoeval/judges/__init__.py
ontoeval/judges/llm_judge.py
ontoeval/judges/metadiff_judge.py
ontoeval/kgcl/__init__.py
ontoeval/kgcl/constants.py
ontoeval/kgcl/evaluator.py
ontoeval/kgcl/llm_agent.py
ontoeval/kgcl/config/__init__.py
ontoeval/kgcl/config/llm_config.py
ontoeval/kgcl/templates/__init__.py
ontoeval/kgcl/templates/templates.py
ontoeval/kgcl/utils/__init__.py
ontoeval/kgcl/utils/general_utils.py
ontoeval/kgcl/utils/llm_utils.py
ontoeval/renderers/markdown.py
ontoeval/runners/claude.py
ontoeval/runners/codex.py
ontoeval/runners/gemini.py
ontoeval/runners/goose.py
ontoeval/utils/argillo_utils.py
ontoeval/utils/diff_summarizer.py
ontoeval/utils/diff_utils.py
ontoeval/utils/replay_diff.py
ontoeval/utils/self_improver.py
ontoeval-0.1.0.dist-info/METADATA
ontoeval-0.1.0.dist-info/WHEEL
ontoeval-0.1.0.dist-info/entry_points.txt
ontoeval-0.1.0.dist-info/licenses/LICENSE
ontoeval-0.1.0.dist-info/RECORD
